terra_ai_datasets/__init__.py
terra_ai_datasets/create.py
terra_ai_datasets/load.py
terra_ai_datasets/creation/__init__.py
terra_ai_datasets/creation/arrays.py
terra_ai_datasets/creation/dataset.py
terra_ai_datasets/creation/preprocessings.py
terra_ai_datasets/creation/utils.py
terra_ai_datasets/creation/visualize.py
terra_ai_datasets/creation/validators/__init__.py
terra_ai_datasets/creation/validators/creation_data.py
terra_ai_datasets/creation/validators/dataset.py
terra_ai_datasets/creation/validators/inputs.py
terra_ai_datasets/creation/validators/outputs.py
terra_ai_datasets/creation/validators/structure.py
terra_ai_datasets/creation/validators/tasks.py
tests/__init__.py
tests/test_classification.py
tests/test_regression.py
tests/test_segmentation.py
tests/test_timeseries.py
terra_ai_datasets-1.1.6.dist-info/METADATA
terra_ai_datasets-1.1.6.dist-info/WHEEL
terra_ai_datasets-1.1.6.dist-info/top_level.txt
terra_ai_datasets-1.1.6.dist-info/RECORD
