Metadata-Version: 2.1
Name: terra-ai-datasets
Version: 1.1.6
Summary: Framework to create a dataset to train a neural network.
Requires-Dist: pydantic (>=1.8.2)
Requires-Dist: pandas (>=1.3.5)
Requires-Dist: opencv-python (>=4.6.0.66)
Requires-Dist: librosa (>=0.8.1)
Requires-Dist: pillow (>=7.1.2)
Requires-Dist: tqdm (>=4.64.1)
Requires-Dist: scikit-learn (>=1.0.2)
Requires-Dist: tensorflow (>=2.0)
Requires-Dist: joblib (>=1.1.0)
Requires-Dist: pymorphy2 (>=0.9.1)
Requires-Dist: gensim (>=3.6.0)
